{
	"msg": "changed",
	"collection": "stream-room-messages",
	"id": "id",
	"fields": {
		"eventName": "__my_messages__",
		"args": [
			{
				"_id": "e4tphAsSkGynLCAvs",
				"rid": "R8TvfTPkA8dj85D3e",
				"msg": "pppppppppppppppppppppppppppppppppp",
				"ts": {
					"$date": 1632668680528
				},
				"u": {
					"_id": "DPt636Ki5GpkLpP4f",
					"username": "a",
					"name": "a"
				},
				"unread": true,
				"_updatedAt": {
					"$date": 1632668680584
				},
				"urls": [],
				"mentions": [],
				"channels": [],
				"md": [
					{
						"type": "PARAGRAPH",
						"value": [
							{
								"type": "PLAIN_TEXT",
								"value": "pppppppppppppppppppppppppppppppppp"
							}
						]
					}
				]
			},
			{
				"roomParticipant": true,
				"roomType": "p",
				"roomName": "xdwy7fn2spggkjiby"
			}
		]
	}
}